actual_module/__init__.py
actual_module/hello_world.py
actual_module-0.0.2.dist-info/METADATA
actual_module-0.0.2.dist-info/WHEEL
actual_module-0.0.2.dist-info/top_level.txt
actual_module-0.0.2.dist-info/RECORD
